tinysumma/__init__.py
tinysumma/main.py
tinysumma/version.py
tinysumma/data/messages.csv
tinysumma/data/urls.csv
tinysumma-0.1.0.dist-info/DESCRIPTION.rst
tinysumma-0.1.0.dist-info/METADATA
tinysumma-0.1.0.dist-info/RECORD
tinysumma-0.1.0.dist-info/WHEEL
tinysumma-0.1.0.dist-info/entry_points.txt
tinysumma-0.1.0.dist-info/metadata.json
tinysumma-0.1.0.dist-info/top_level.txt
