Metadata-Version: 2.0
Name: tinysumma
Version: 0.1.0
Summary: Summarize tinyletter statistics
Home-page: https://github.com/awbirdsall/tinysumma
Author: Adam Birdsall
Author-email: abirdsall@gmail.com
License: MIT
Keywords: newsletter,tinyletter,command line,cli
Platform: UNKNOWN
Classifier: Development Status :: 3 - Alpha
Classifier: License :: OSI Approved :: MIT License
Classifier: Programming Language :: Python :: 3
Classifier: Programming Language :: Python :: 3.5
Requires-Dist: pandas
Requires-Dist: tinyapi
